flaskr/__init__.py
flaskr/auth.py
flaskr/blog.py
flaskr/db.py
flaskr/schema.sql
flaskr/static/style.css
flaskr/templates/base.html
flaskr/templates/auth/login.html
flaskr/templates/auth/register.html
flaskr/templates/blog/create.html
flaskr/templates/blog/index.html
flaskr/templates/blog/update.html
flaskrrr-1.0.0.dist-info/METADATA
flaskrrr-1.0.0.dist-info/WHEEL
flaskrrr-1.0.0.dist-info/top_level.txt
flaskrrr-1.0.0.dist-info/RECORD
