Metadata-Version: 2.1
Name: flaskrrr
Version: 1.0.0
Summary: The basic blog app built in the Flask tutorial.
Home-page: http://flask.pocoo.org/docs/tutorial/
Maintainer: Pallets team
Maintainer-email: ouyangwenli@gmail.com
License: BSD
Platform: UNKNOWN
Requires-Dist: flask
Provides-Extra: test
Requires-Dist: pytest ; extra == 'test'
Requires-Dist: coverage ; extra == 'test'
